constelite/__init__.py
constelite/api/__init__.py
constelite/api/api.py
constelite/api/camunda/__init__.py
constelite/api/camunda/api.py
constelite/api/camunda/defs.py
constelite/api/camunda/template_generator.py
constelite/api/redis/__init__.py
constelite/api/redis/api.py
constelite/api/starlite/__init__.py
constelite/api/starlite/api.py
constelite/api/starlite/async_client.py
constelite/api/starlite/client.py
constelite/api/starlite/controllers/__init__.py
constelite/api/starlite/controllers/generator.py
constelite/api/starlite/controllers/jobs.py
constelite/api/starlite/controllers/models.py
constelite/api/starlite/controllers/protocols.py
constelite/api/starlite/controllers/store.py
constelite/config.py
constelite/graphql/__init__.py
constelite/graphql/field_type_map.py
constelite/graphql/schema.py
constelite/graphql/utils.py
constelite/guid_map/__init__.py
constelite/guid_map/async_base.py
constelite/guid_map/async_neo4j.py
constelite/guid_map/memory.py
constelite/guid_map/sync_base.py
constelite/guid_map/sync_neo4j.py
constelite/hook.py
constelite/loggers/__init__.py
constelite/loggers/base_logger.py
constelite/models/__init__.py
constelite/models/auto_resolve.py
constelite/models/dynamic.py
constelite/models/inspector.py
constelite/models/model.py
constelite/models/object.py
constelite/models/ref.py
constelite/models/relationships.py
constelite/models/resolve.py
constelite/models/store.py
constelite/models/tensor.py
constelite/protocol.py
constelite/store/__init__.py
constelite/store/base.py
constelite/store/base_async.py
constelite/store/memcached.py
constelite/store/memory.py
constelite/store/neoflux.py
constelite/store/pickle.py
constelite/store/queries.py
constelite/store/uid_key_base.py
constelite/utils.py
constelite-1.0.0.dist-info/METADATA
constelite-1.0.0.dist-info/WHEEL
constelite-1.0.0.dist-info/RECORD
